llm_web_research/__about__.py
llm_web_research/__init__.py
llm_web_research/_baseline.py
llm_web_research/precise_search.py
llm_web_research/search.py
llm_web_research/tavily_search.py
llm_web_research/calls/__init__.py
llm_web_research/calls/all_calls.py
llm_web_research/calls/prompts.py
llm_web_research-0.0.3.dist-info/METADATA
llm_web_research-0.0.3.dist-info/WHEEL
llm_web_research-0.0.3.dist-info/licenses/LICENSE
llm_web_research-0.0.3.dist-info/RECORD
