Metadata-Version: 2.4
Name: llm-web-research
Version: 0.0.3
Summary: A precision-focused LLM-powered web research tool that prioritizes accuracy over quantity
Project-URL: Documentation, https://github.com/chrissoria/llm-web-research#readme
Project-URL: Issues, https://github.com/chrissoria/llm-web-research/issues
Project-URL: Source, https://github.com/chrissoria/llm-web-research
Author-email: Chris Soria <chrissoria@berkeley.edu>
License-Expression: GPL-3.0
License-File: LICENSE
Keywords: accuracy,fact checking,information retrieval,llm,precision,search,web research
Classifier: Development Status :: 3 - Alpha
Classifier: Programming Language :: Python
Classifier: Programming Language :: Python :: 3.8
Classifier: Programming Language :: Python :: 3.9
Classifier: Programming Language :: Python :: 3.10
Classifier: Programming Language :: Python :: 3.11
Classifier: Programming Language :: Python :: 3.12
Classifier: Programming Language :: Python :: Implementation :: CPython
Classifier: Programming Language :: Python :: Implementation :: PyPy
Requires-Python: >=3.8
Requires-Dist: anthropic
Requires-Dist: pandas
Requires-Dist: regex
Requires-Dist: requests
Requires-Dist: tqdm
